{"name":"KhmerOSSiemreap","type":"TTF","desc":{"CapHeight":732,"XHeight":557,"FontBBox":"[-1184 -586 2173 1222]","Flags":68,"Ascent":1221,"Descent":-586,"Leading":0,"ItalicAngle":9,"StemV":87,"MissingWidth":0},"unitsPerEm":2048,"up":-146,"ut":23,"strp":259,"strs":50,"ttffile":"\/Users\/yusonghoun\/Web Software\/construction\/resources\/fonts\/\/KhmerOSsiemreap.ttf","TTCfontID":0,"originalsize":132220,"sip":false,"smp":false,"BMPselected":false,"fontkey":"khmerfont","panose":" 0 0 2 0 5 0 0 0 0 2 0 4","haskerninfo":true,"haskernGPOS":false,"hassmallcapsGSUB":false,"fontmetrics":"win","useOTL":255,"rtlPUAstr":"","GSUBScriptLang":{"khmr":"DFLT "},"GSUBFeatures":{"khmr":{"DFLT":{"abvf":[0],"pref":[2],"blwf":[3,17,18],"blws":[4,5],"pstf":[6],"pres":[7,8,9,10,11,12],"abvs":[13],"psts":[14],"clig":[15,16]}}},"GSUBLookups":[{"Type":1,"Flag":0,"SubtableCount":1,"Subtables":[111826],"MarkFilteringSet":""},{"Type":6,"Flag":0,"SubtableCount":1,"Subtables":[111840],"MarkFilteringSet":""},{"Type":4,"Flag":0,"SubtableCount":1,"Subtables":[111916],"MarkFilteringSet":""},{"Type":4,"Flag":0,"SubtableCount":1,"Subtables":[111940],"MarkFilteringSet":""},{"Type":6,"Flag":0,"SubtableCount":2,"Subtables":[112308,112326],"MarkFilteringSet":""},{"Type":6,"Flag":0,"SubtableCount":1,"Subtables":[112378],"MarkFilteringSet":""},{"Type":4,"Flag":0,"SubtableCount":1,"Subtables":[112408],"MarkFilteringSet":""},{"Type":6,"Flag":0,"SubtableCount":1,"Subtables":[112536],"MarkFilteringSet":""},{"Type":6,"Flag":0,"SubtableCount":2,"Subtables":[112630,112650],"MarkFilteringSet":""},{"Type":6,"Flag":0,"SubtableCount":3,"Subtables":[112764,112786,112808],"MarkFilteringSet":""},{"Type":6,"Flag":0,"SubtableCount":1,"Subtables":[113078],"MarkFilteringSet":""},{"Type":6,"Flag":0,"SubtableCount":1,"Subtables":[113108],"MarkFilteringSet":""},{"Type":6,"Flag":0,"SubtableCount":1,"Subtables":[113148],"MarkFilteringSet":""},{"Type":4,"Flag":0,"SubtableCount":1,"Subtables":[113186],"MarkFilteringSet":""},{"Type":6,"Flag":0,"SubtableCount":1,"Subtables":[113210],"MarkFilteringSet":""},{"Type":4,"Flag":8,"SubtableCount":1,"Subtables":[113314],"MarkFilteringSet":""},{"Type":4,"Flag":8,"SubtableCount":1,"Subtables":[114378],"MarkFilteringSet":""},{"Type":6,"Flag":0,"SubtableCount":9,"Subtables":[115042,115062,115084,115104,115126,115150,115172,115196,115220],"MarkFilteringSet":""},{"Type":6,"Flag":0,"SubtableCount":9,"Subtables":[115886,115906,115928,115948,115968,115990,116014,116036,116060],"MarkFilteringSet":""},{"Type":1,"Flag":0,"SubtableCount":1,"Subtables":[116694],"MarkFilteringSet":""},{"Type":1,"Flag":0,"SubtableCount":1,"Subtables":[116708],"MarkFilteringSet":""},{"Type":1,"Flag":0,"SubtableCount":1,"Subtables":[116722],"MarkFilteringSet":""},{"Type":1,"Flag":0,"SubtableCount":1,"Subtables":[116736],"MarkFilteringSet":""},{"Type":1,"Flag":0,"SubtableCount":1,"Subtables":[116750],"MarkFilteringSet":""},{"Type":1,"Flag":0,"SubtableCount":1,"Subtables":[116772],"MarkFilteringSet":""},{"Type":1,"Flag":0,"SubtableCount":1,"Subtables":[116794],"MarkFilteringSet":""},{"Type":1,"Flag":0,"SubtableCount":1,"Subtables":[116808],"MarkFilteringSet":""},{"Type":1,"Flag":0,"SubtableCount":1,"Subtables":[116822],"MarkFilteringSet":""},{"Type":1,"Flag":0,"SubtableCount":1,"Subtables":[116836],"MarkFilteringSet":""},{"Type":1,"Flag":0,"SubtableCount":1,"Subtables":[116912],"MarkFilteringSet":""},{"Type":1,"Flag":0,"SubtableCount":1,"Subtables":[116926],"MarkFilteringSet":""}],"GPOSScriptLang":{"khmr":"DFLT "},"GPOSFeatures":{"khmr":{"DFLT":{"blwm":[0,1,2],"mkmk":[2],"abvm":[3,4,5]}}},"GPOSLookups":[{"Type":5,"Flag":0,"SubtableCount":1,"Subtables":[106798],"MarkFilteringSet":""},{"Type":4,"Flag":0,"SubtableCount":1,"Subtables":[108136],"MarkFilteringSet":""},{"Type":6,"Flag":0,"SubtableCount":1,"Subtables":[108662],"MarkFilteringSet":""},{"Type":4,"Flag":0,"SubtableCount":1,"Subtables":[109186],"MarkFilteringSet":""},{"Type":5,"Flag":0,"SubtableCount":1,"Subtables":[109524],"MarkFilteringSet":""},{"Type":6,"Flag":0,"SubtableCount":1,"Subtables":[110692],"MarkFilteringSet":""}],"kerninfo":{"84":{"97":-97}}}